esmtools/__init__.py
esmtools/accessor.py
esmtools/carbon.py
esmtools/checks.py
esmtools/composite.py
esmtools/constants.py
esmtools/conversions.py
esmtools/exceptions.py
esmtools/grid.py
esmtools/physics.py
esmtools/spatial.py
esmtools/stats.py
esmtools/temporal.py
esmtools/testing.py
esmtools/timeutils.py
esmtools/utils.py
esmtools/versioning/__init__.py
esmtools/versioning/print_versions.py
esmtools-1.1.3.dist-info/LICENSE.txt
esmtools-1.1.3.dist-info/METADATA
esmtools-1.1.3.dist-info/WHEEL
esmtools-1.1.3.dist-info/top_level.txt
esmtools-1.1.3.dist-info/RECORD
