Metadata-Version: 2.1
Name: esmtools
Version: 1.1.3
Summary: a toolbox for Earth System Model analysis
Home-page: https://github.com/bradyrx/esmtools
Maintainer: Riley X. Brady
Maintainer-email: riley.brady@colorado.edu
License: MIT
Platform: UNKNOWN
Classifier: Development Status :: 3 - Alpha
Classifier: License :: OSI Approved :: MIT License
Classifier: Operating System :: OS Independent
Classifier: Intended Audience :: Science/Research
Classifier: Programming Language :: Python :: 3 :: Only
Classifier: Programming Language :: Python :: 3.6
Classifier: Programming Language :: Python :: 3.7
Classifier: Programming Language :: Python :: 3.8
Requires-Python: >=3.6
Requires-Dist: cftime
Requires-Dist: numpy
Requires-Dist: scipy
Requires-Dist: statsmodels
Requires-Dist: tqdm
Requires-Dist: xarray (>=0.16.0)
Requires-Dist: xskillscore
